django_tastypie_sorl_thumbnail-0.1.5.dist-info/DESCRIPTION.rst
django_tastypie_sorl_thumbnail-0.1.5.dist-info/METADATA
django_tastypie_sorl_thumbnail-0.1.5.dist-info/RECORD
django_tastypie_sorl_thumbnail-0.1.5.dist-info/WHEEL
django_tastypie_sorl_thumbnail-0.1.5.dist-info/metadata.json
django_tastypie_sorl_thumbnail-0.1.5.dist-info/top_level.txt
tastypie_sorl_thumbnail/__init__.py
tastypie_sorl_thumbnail/fields.py
tastypie_sorl_thumbnail/models.py
